ubyte/__init__.py
ubyte-0.2.0.dist-info/LICENSE.txt
ubyte-0.2.0.dist-info/METADATA
ubyte-0.2.0.dist-info/WHEEL
ubyte-0.2.0.dist-info/top_level.txt
ubyte-0.2.0.dist-info/RECORD
