Metadata-Version: 2.1
Name: ubyte
Version: 0.2.0
Summary: A package to decode .idx*-ubyte file.
Home-page: https://github.com/JunzePeng/ubyte
Author: JunzePeng
Author-email: gxp@bupt.edu.cn
License: MIT
Classifier: License :: OSI Approved :: MIT License
Classifier: Programming Language :: Python :: 3.11
Classifier: Operating System :: OS Independent
Requires-Python: >=3.1.0
License-File: LICENSE.txt
